arcade_microsoft_teams/__init__.py
arcade_microsoft_teams/api_filtering_utils.py
arcade_microsoft_teams/client.py
arcade_microsoft_teams/concurency.py
arcade_microsoft_teams/conftest.py
arcade_microsoft_teams/constants.py
arcade_microsoft_teams/critics.py
arcade_microsoft_teams/exceptions.py
arcade_microsoft_teams/models.py
arcade_microsoft_teams/serializers.py
arcade_microsoft_teams/utils.py
arcade_microsoft_teams/who_am_i_util.py
arcade_microsoft_teams/evals/channel/eval_get_channel.py
arcade_microsoft_teams/evals/channel/eval_get_channel_message_replies.py
arcade_microsoft_teams/evals/channel/eval_get_channel_messages.py
arcade_microsoft_teams/evals/channel/eval_list_channels.py
arcade_microsoft_teams/evals/channel/eval_search_channels.py
arcade_microsoft_teams/evals/channel/eval_send_message_to_channel.py
arcade_microsoft_teams/evals/chat/eval_create_chat.py
arcade_microsoft_teams/evals/chat/eval_get_chat_messages.py
arcade_microsoft_teams/evals/chat/eval_get_chat_metadata.py
arcade_microsoft_teams/evals/chat/eval_list_chats.py
arcade_microsoft_teams/evals/chat/eval_send_message_to_chat.py
arcade_microsoft_teams/evals/people/eval_search_people.py
arcade_microsoft_teams/evals/search/eval_search_messages.py
arcade_microsoft_teams/evals/teams/eval_get_team.py
arcade_microsoft_teams/evals/teams/eval_list_team_members.py
arcade_microsoft_teams/evals/teams/eval_list_teams.py
arcade_microsoft_teams/evals/teams/eval_search_team_members.py
arcade_microsoft_teams/evals/teams/eval_search_teams.py
arcade_microsoft_teams/evals/users/eval_list_users.py
arcade_microsoft_teams/evals/users/eval_search_users.py
arcade_microsoft_teams/tests/test_api_filtering_utils.py
arcade_microsoft_teams/tests/test_concurrency.py
arcade_microsoft_teams/tests/test_find_people_by_name.py
arcade_microsoft_teams/tests/test_sentinels.py
arcade_microsoft_teams/tests/test_who_am_i_util.py
arcade_microsoft_teams/tools/__init__.py
arcade_microsoft_teams/tools/channel.py
arcade_microsoft_teams-0.4.1.dist-info/METADATA
arcade_microsoft_teams-0.4.1.dist-info/WHEEL
arcade_microsoft_teams-0.4.1.dist-info/licenses/LICENSE
arcade_microsoft_teams-0.4.1.dist-info/RECORD
