Metadata-Version: 2.4
Name: arcade_microsoft_teams
Version: 0.4.1
Summary: Arcade.dev LLM tools for Microsoft Teams
Author-email: Arcade <dev@arcade.dev>
License-File: LICENSE
Requires-Python: <4.0,>=3.10
Requires-Dist: arcade-tdk<4.0.0,>=3.0.0
Requires-Dist: msgraph-beta-sdk<1.40.0,>=1.39.0
Requires-Dist: msgraph-sdk<2.0.0,>=1.28.0
Provides-Extra: dev
Requires-Dist: arcade-mcp[evals]<2.0.0,>=1.1.0; extra == 'dev'
Requires-Dist: arcade-serve<4.0.0,>=3.0.0; extra == 'dev'
Requires-Dist: mypy<1.6.0,>=1.5.1; extra == 'dev'
Requires-Dist: pre-commit<3.5.0,>=3.4.0; extra == 'dev'
Requires-Dist: pytest-asyncio<0.25.0,>=0.24.0; extra == 'dev'
Requires-Dist: pytest-cov<4.1.0,>=4.0.0; extra == 'dev'
Requires-Dist: pytest-mock<3.15.0,>=3.14.1; extra == 'dev'
Requires-Dist: pytest<8.4.0,>=8.3.0; extra == 'dev'
Requires-Dist: ruff<0.8.0,>=0.7.4; extra == 'dev'
Requires-Dist: tox<4.12.0,>=4.11.1; extra == 'dev'
